LICENSE.txt
README.rst
setup.py
SMCLIB/__init__.py
SMClib.py.egg-info/PKG-INFO
SMClib.py.egg-info/SOURCES.txt
SMClib.py.egg-info/dependency_links.txt
SMClib.py.egg-info/requires.txt
SMClib.py.egg-info/top_level.txt