Metadata-Version: 2.1
Name: SMClib.py
Version: 1.0.8
Summary: biblioteka ułatwiająca prace przy discord botach
Home-page: 
Author: ESKARABATOS
Author-email: bartek.torba@interia.pl
License: MIT
Keywords: SMC Discord
Classifier: Development Status :: 5 - Production/Stable
Classifier: Intended Audience :: Education
Classifier: Operating System :: Microsoft :: Windows :: Windows 10
Classifier: License :: OSI Approved :: MIT License
Classifier: Programming Language :: Python :: 3
License-File: LICENSE.txt
